langchain_mcp_adapters/__init__.py
langchain_mcp_adapters/client.py
langchain_mcp_adapters/prompts.py
langchain_mcp_adapters/resources.py
langchain_mcp_adapters/tools.py
langchain_nostr_mcp_adapters-0.0.3.dist-info/licenses/LICENSE
langchain_nostr_mcp_adapters-0.0.3.dist-info/METADATA
langchain_nostr_mcp_adapters-0.0.3.dist-info/WHEEL
langchain_nostr_mcp_adapters-0.0.3.dist-info/top_level.txt
langchain_nostr_mcp_adapters-0.0.3.dist-info/RECORD
