Metadata-Version: 2.4
Name: langchain-nostr-mcp-adapters
Version: 0.0.3
Summary: Make Anthropic Model Context Protocol (MCP) tools compatible with LangChain and LangGraph agents.
Author-email: Vadym Barda <19161700+vbarda@users.noreply.github.com>, Evan Hallmark <ehallmark1122@gmail.com>
License-Expression: MIT
Project-URL: Homepage, https://www.github.com/ehallmark/langchain-mcp-adapters
Project-URL: Issues, https://www.github.com/ehallmark/langchain-mcp-adapters/issues
Requires-Python: >=3.11
License-File: LICENSE
Requires-Dist: langchain-core<0.4,>=0.3.36
Requires-Dist: mcp>=1.7
Requires-Dist: nostr-agent-tools>=0.5.0
Dynamic: license-file
